src/__init__.py
src/auth.py
src/client.py
src/main.py
arvan_cli-0.0.1a5.dist-info/LICENSE
arvan_cli-0.0.1a5.dist-info/METADATA
arvan_cli-0.0.1a5.dist-info/WHEEL
arvan_cli-0.0.1a5.dist-info/entry_points.txt
arvan_cli-0.0.1a5.dist-info/top_level.txt
arvan_cli-0.0.1a5.dist-info/RECORD
