Metadata-Version: 2.1
Name: arvan-cli
Version: 0.0.1a5
Summary: A Command Line Tool to Work with ArvanCloud
Home-page: https://github.com/Parsa2820/arvan-cli
Author: Parsa Mohammadian
Author-email: parsa2820@gmail.com
License: GPL-3.0
Requires-Python: >=3.6
License-File: LICENSE
Requires-Dist: typer
